mni_to_atlas/__init__.py
mni_to_atlas/atlas_browser.py
mni_to_atlas/atlases/AAL.nii
mni_to_atlas/atlases/AAL.txt
mni_to_atlas/atlases/AAL3.nii
mni_to_atlas/atlases/AAL3.txt
mni_to_atlas/atlases/HCPEx.nii
mni_to_atlas/atlases/HCPEx.txt
mni_to_atlas/atlases/__init__.py
mni_to_atlas-1.1.0.dist-info/METADATA
mni_to_atlas-1.1.0.dist-info/WHEEL
mni_to_atlas-1.1.0.dist-info/licenses/LICENSE.txt
mni_to_atlas-1.1.0.dist-info/RECORD
