Metadata-Version: 2.1
Name: mni-to-atlas
Version: 1.1.0
Summary: A simple Python-based tool for finding brain atlas regions based on MNI coordinates.
Project-URL: Homepage, https://github.com/tsbinns/mni_to_atlas
Project-URL: Bug Tracker, https://github.com/tsbinns/mni_to_atlas/issues
Author-email: Thomas Samuel Binns <t.s.binns@outlook.com>
License-File: LICENSE.txt
Classifier: License :: OSI Approved :: MIT License
Classifier: Operating System :: OS Independent
Classifier: Programming Language :: Python :: 3
Requires-Python: >=3.10
Requires-Dist: matplotlib>=3.5
Requires-Dist: nibabel>=3.2
Requires-Dist: numpy>=1.22
Provides-Extra: dev
Requires-Dist: black; extra == 'dev'
Requires-Dist: codespell; extra == 'dev'
Requires-Dist: coverage; extra == 'dev'
Requires-Dist: flake8; extra == 'dev'
Requires-Dist: pycodestyle; extra == 'dev'
Requires-Dist: pydocstyle; extra == 'dev'
Requires-Dist: pytest; extra == 'dev'
